accloudtant/__init__.py
accloudtant/aws/__init__.py
accloudtant/aws/instance.py
accloudtant/aws/prices.py
accloudtant/aws/reports.py
accloudtant/aws/reserved_instance.py
accloudtant/utils/__init__.py
accloudtant-0.1.4.data/scripts/accloudtant
accloudtant-0.1.4.dist-info/DESCRIPTION.rst
accloudtant-0.1.4.dist-info/METADATA
accloudtant-0.1.4.dist-info/RECORD
accloudtant-0.1.4.dist-info/WHEEL
accloudtant-0.1.4.dist-info/metadata.json
accloudtant-0.1.4.dist-info/top_level.txt
