Metadata-Version: 2.0
Name: accloudtant
Version: 0.1.4
Summary: Cloud cost calculation tool
Home-page: https://github.com/ifosch/accloudtant
Author: Ignasi Fosch, Eduardo Bellido Bellido, David Arcos
Author-email: accloudtant@y10k.ws
License: UNKNOWN
Download-URL: https://github.com/ifosch/accloudtant/archive/0.1.4
Keywords: cloud,AWS,costs
Platform: UNKNOWN
Classifier: Development Status :: 5 - Production/Stable
Classifier: Environment :: Console
Classifier: Intended Audience :: Developers
Classifier: Intended Audience :: System Administrators
Classifier: License :: OSI Approved :: Apache Software License
Classifier: Topic :: Office/Business :: Financial :: Investment
Requires-Dist: boto3
Requires-Dist: click
Requires-Dist: requests
Requires-Dist: tabulate
